pypactl/async_callback.py
pypactl/channel_map.py
pypactl/command.py
pypactl/command_error.py
pypactl/console.py
pypactl/controller.py
pypactl/cvolume.py
pypactl/error_code.py
pypactl/event.py
pypactl/format_info.py
pypactl/invalid_packet.py
pypactl/loop.py
pypactl/native_protocol.py
pypactl/native_protocol_sink_info.py
pypactl/native_transport.py
pypactl/packet.py
pypactl/protocol.py
pypactl/pypactl.py
pypactl/sample_spec.py
pypactl/server_info.py
pypactl/sink_info.py
pypactl/sink_port_info.py
pypactl/subscription_event_type.py
pypactl/subscription_mask.py
pypactl/tag.py
pypactl-0.1.3.dist-info/entry_points.txt
pypactl-0.1.3.dist-info/LICENSE
pypactl-0.1.3.dist-info/WHEEL
pypactl-0.1.3.dist-info/METADATA
pypactl-0.1.3.dist-info/RECORD
