Metadata-Version: 2.1
Name: pypactl
Version: 0.1.3
Summary: Sends commands and gets information from PulseAudio.
Home-page: https://github.com/Dawnthorn/pypactl
License: GPL-3.0-only
Author: Peter Haight
Author-email: peterh@giantrabbit.com
Requires-Python: >=3.10,<4.0
Classifier: License :: OSI Approved :: GNU General Public License v3 (GPLv3)
Classifier: Programming Language :: Python :: 3
Classifier: Programming Language :: Python :: 3.10
Requires-Dist: aioconsole (>=0.5.0,<0.6.0)
Project-URL: Repository, https://github.com/Dawnthorn/pypactl
